dialogflow_handler/__init__.py
dialogflow_handler/agent.py
dialogflow_handler-0.1.6.dist-info/LICENSE
dialogflow_handler-0.1.6.dist-info/METADATA
dialogflow_handler-0.1.6.dist-info/WHEEL
dialogflow_handler-0.1.6.dist-info/top_level.txt
dialogflow_handler-0.1.6.dist-info/RECORD
