Metadata-Version: 2.1
Name: dialogflow-handler
Version: 0.1.6
Summary: Another Dialogflow API wrapper
Home-page: https://github.com/ecnivs/dialogflow-handler
Author: Vince Swu
Author-email: vinceswu88@gmail.com
Classifier: Programming Language :: Python :: 3
Classifier: License :: OSI Approved :: MIT License
Classifier: Operating System :: OS Independent
Requires-Python: >=3.6
License-File: LICENSE
Requires-Dist: google-cloud-dialogflow
Requires-Dist: google-api-core
